LICENSE
MANIFEST.in
README.md
requirements.txt
setup.py
django_postmark_inbound.egg-info/PKG-INFO
django_postmark_inbound.egg-info/SOURCES.txt
django_postmark_inbound.egg-info/dependency_links.txt
django_postmark_inbound.egg-info/requires.txt
django_postmark_inbound.egg-info/top_level.txt
postmark_inbound/__init__.py
postmark_inbound/admin.py
postmark_inbound/apps.py
postmark_inbound/models.py
postmark_inbound/parsers.py
postmark_inbound/serializers.py
postmark_inbound/settings.py
postmark_inbound/signals.py
postmark_inbound/urls.py
postmark_inbound/utils.py
postmark_inbound/views.py